{
  "andhra": "AP",
  "pradesh": "UP",
  "arunachal": "AR",
  "assam": "AS",
  "bihar": "BR",
  "chhattisgarh": "CT",
  "goa": "GA",
  "gujarat": "GJ",
  "haryana": "HR",
  "himachal": "HP",
  "jammu": "JK",
  "and": "DD",
  "kashmir": "JK",
  "jharkhand": "JH",
  "karnataka": "KA",
  "kerala": "KL",
  "madhya": "MP",
  "maharashtra": "MH",
  "manipur": "MN",
  "meghalaya": "ML",
  "mizoram": "MZ",
  "nagaland": "NL",
  "odisha": "OR",
  "punjab": "PB",
  "rajasthan": "RJ",
  "sikkim": "SK",
  "tamil": "TN",
  "nadu": "TN",
  "telangana": "TG",
  "tripura": "TR",
  "uttarakhand": "UT",
  "uttar": "UP",
  "west": "WB",
  "bengal": "WB",
  "andaman": "AN",
  "nicobar": "AN",
  "islands": "AN",
  "chandigarh": "CH",
  "dadra": "DN",
  "nagar": "DN",
  "haveli": "DN",
  "daman": "DD",
  "diu": "DD",
  "delhi": "DL",
  "lakshadweep": "LD",
  "puducherry": "PY"
}
